pyniviz/__init__.py
pyniviz/main.py
pyniviz/tools.py
pyniviz-1.1.3.dist-info/LICENCE.txt
pyniviz-1.1.3.dist-info/METADATA
pyniviz-1.1.3.dist-info/WHEEL
pyniviz-1.1.3.dist-info/top_level.txt
pyniviz-1.1.3.dist-info/RECORD
