Metadata-Version: 2.1
Name: pyniviz
Version: 1.1.3
Summary: UNKNOWN
Home-page: https://github.com/robbiemallett/pyniviz
Author: Robbie Mallett
Author-email: robbie.mallett.17@ucl.ac.uk
License: UNKNOWN
Platform: UNKNOWN
Requires-Dist: pandas
Requires-Dist: numpy
Requires-Dist: scipy
Requires-Dist: matplotlib
Requires-Dist: docutils
Requires-Dist: Pygments
